{
  "niveau": "TSPE",
  "theme": "SUITES-LIMITES",
  "bo_reference": "Programme de spécialité mathématiques de terminale générale, BO spécial n°8 du 25 juillet 2019 — Analyse / Suites",
  "note": "Formulations libelle_bo extraites de sources/BO2019_TSPE_specialite.txt, section Suites. R7 vérifié.",
  "capacites": [
    {
      "id": "TSPE-SUITLIM-C1",
      "libelle_bo": "Établir la convergence d'une suite, ou sa divergence vers + ∞ ou – ∞.",
      "libelle_eleve": "Je sais établir la convergence ou la divergence d'une suite en utilisant les outils adaptés (comparaison, gendarmes, suite monotone bornée).",
      "demonstration_exigible": false
    },
    {
      "id": "TSPE-SUITLIM-C2",
      "libelle_bo": "Raisonner par récurrence pour établir une propriété d'une suite.",
      "libelle_eleve": "Je sais démontrer une propriété d'une suite par récurrence.",
      "demonstration_exigible": false
    },
    {
      "id": "TSPE-SUITLIM-C3",
      "libelle_bo": "Étudier des phénomènes d'évolution modélisables par une suite.",
      "libelle_eleve": "Je sais modéliser et étudier un phénomène d'évolution à l'aide d'une suite.",
      "demonstration_exigible": false
    },
    {
      "id": "TSPE-SUITLIM-C4",
      "libelle_bo": "Toute suite croissante non majorée tend vers + ∞.",
      "libelle_eleve": "Je sais démontrer que toute suite croissante non majorée tend vers + ∞.",
      "demonstration_exigible": true,
      "demonstration": "Toute suite croissante non majorée tend vers + ∞."
    },
    {
      "id": "TSPE-SUITLIM-C5",
      "libelle_bo": "Limite de (q^n), après démonstration par récurrence de l'inégalité de Bernoulli.",
      "libelle_eleve": "Je sais démontrer l'inégalité de Bernoulli par récurrence et en déduire la limite de (q^n).",
      "demonstration_exigible": true,
      "demonstration": "Limite de (q^n), après démonstration par récurrence de l'inégalité de Bernoulli."
    },
    {
      "id": "TSPE-SUITLIM-C6",
      "libelle_bo": "Divergence vers + ∞ d'une suite minorée par une suite divergeant vers + ∞.",
      "libelle_eleve": "Je sais démontrer la divergence d'une suite par minoration par une suite divergente.",
      "demonstration_exigible": true,
      "demonstration": "Divergence vers + ∞ d'une suite minorée par une suite divergeant vers + ∞."
    },
    {
      "id": "TSPE-SUITLIM-C7",
      "libelle_bo": "Limite en + ∞ et en – ∞ de la fonction exponentielle.",
      "libelle_eleve": "Je sais démontrer les limites de la fonction exponentielle en + ∞ et en – ∞.",
      "demonstration_exigible": true,
      "demonstration": "Limite en + ∞ et en – ∞ de la fonction exponentielle."
    }
  ]
}
